tiepy/__init__.py
tiepy/cli.py
tiepy/overrides.py
tiepy/check/__init__.py
tiepy/check/overrides.py
tiepy-0.0.1.dist-info/LICENSE
tiepy-0.0.1.dist-info/METADATA
tiepy-0.0.1.dist-info/WHEEL
tiepy-0.0.1.dist-info/entry_points.txt
tiepy-0.0.1.dist-info/top_level.txt
tiepy-0.0.1.dist-info/RECORD
